frames_zoom/__init__.py
frames_zoom/example.py
frames_zoom/frontend/.env
frames_zoom/frontend/.gitignore
frames_zoom/frontend/.prettierrc
frames_zoom/frontend/package-lock.json
frames_zoom/frontend/package.json
frames_zoom/frontend/public/bootstrap.min.css
frames_zoom/frontend/public/index.html
frames_zoom/frontend/src/FramesZoom.tsx
frames_zoom/frontend/src/components/ZoomRectangleManager.tsx
frames_zoom/frontend/src/index.tsx
frames_zoom/frontend/src/react-app-env.d.ts
frames_zoom/frontend/tsconfig.json
frames_zoom/version.py
frames_zoom-0.1.0.dist-info/LICENSE
frames_zoom-0.1.0.dist-info/METADATA
frames_zoom-0.1.0.dist-info/WHEEL
frames_zoom-0.1.0.dist-info/RECORD
