Metadata-Version: 2.1
Name: frames_zoom
Version: 0.1.0
Summary: 
Author: José Beltrán
Requires-Python: >=3.11,<4.0
Classifier: Programming Language :: Python :: 3
Classifier: Programming Language :: Python :: 3.11
Classifier: Programming Language :: Python :: 3.12
Requires-Dist: pillow (>=10.2.0,<11.0.0)
